redactor/__init__.py
redactor/core.py
redactor/patterns.py
tests/__init__.py
tests/test_redactor.py
redactor-0.1.0.dist-info/LICENSE
redactor-0.1.0.dist-info/METADATA
redactor-0.1.0.dist-info/WHEEL
redactor-0.1.0.dist-info/top_level.txt
redactor-0.1.0.dist-info/RECORD
